flashlearners_core/__init__.py
flashlearners_core/constants.py
flashlearners_core/settings.py
flashlearners_core/utils.py
flashlearners_core/app/__init__.py
flashlearners_core/app/admin.py
flashlearners_core/app/apps.py
flashlearners_core/app/signals.py
flashlearners_core/app/fields/__init__.py
flashlearners_core/app/fields/media_field.py
flashlearners_core/app/managers/__init__.py
flashlearners_core/app/managers/notification_manager.py
flashlearners_core/app/migrations/0001_initial.py
flashlearners_core/app/migrations/0002_remove_flashcard_subject_remove_video_subject_and_more.py
flashlearners_core/app/migrations/0003_alter_subject_image.py
flashlearners_core/app/migrations/0004_remove_video_media_video_file_video_title_and_more.py
flashlearners_core/app/migrations/0005_novel_is_active_novelchapter_is_active_and_more.py
flashlearners_core/app/migrations/0006_remove_option_image_remove_question_image_and_more.py
flashlearners_core/app/migrations/0007_feedback_image1_feedback_image2.py
flashlearners_core/app/migrations/0008_token.py
flashlearners_core/app/migrations/0009_remove_user_current_subscription_and_more.py
flashlearners_core/app/migrations/0010_delete_token_and_more.py
flashlearners_core/app/migrations/0011_alter_performance_type_alter_question_category.py
flashlearners_core/app/migrations/0012_remove_subject_current_affair.py
flashlearners_core/app/migrations/0013_alter_video_file.py
flashlearners_core/app/migrations/__init__.py
flashlearners_core/app/models/__init__.py
flashlearners_core/app/models/base.py
flashlearners_core/app/models/bookmark.py
flashlearners_core/app/models/faq.py
flashlearners_core/app/models/feedback.py
flashlearners_core/app/models/flashcard.py
flashlearners_core/app/models/guide.py
flashlearners_core/app/models/media.py
flashlearners_core/app/models/notification.py
flashlearners_core/app/models/payment.py
flashlearners_core/app/models/performance.py
flashlearners_core/app/models/quiz.py
flashlearners_core/app/models/subject.py
flashlearners_core-0.1.3.dist-info/LICENSE
flashlearners_core-0.1.3.dist-info/METADATA
flashlearners_core-0.1.3.dist-info/WHEEL
flashlearners_core-0.1.3.dist-info/top_level.txt
flashlearners_core-0.1.3.dist-info/RECORD
