Metadata-Version: 2.1
Name: flashlearners_core
Version: 0.1.3
Summary: FlashLearners core package
Author: Folayemi Bello
Author-email: <bello.folayemi.az@gmail.com>
Keywords: python,FlashLearners
Classifier: Programming Language :: Python :: 3
Classifier: License :: OSI Approved :: MIT License
Classifier: Operating System :: OS Independent
License-File: LICENSE
Requires-Dist: django
Requires-Dist: python-dotenv
Requires-Dist: django-elasticsearch-dsl
Requires-Dist: django-environ
Requires-Dist: onesignal-sdk
Requires-Dist: daphne
Requires-Dist: psycopg2-binary
Requires-Dist: uvicorn
Requires-Dist: django-storages
Requires-Dist: boto3
Requires-Dist: pymysql
Requires-Dist: django-ckeditor-5
